synapse_registration/manage.py
synapse_registration/registration/__init__.py
synapse_registration/registration/admin.py
synapse_registration/registration/apps.py
synapse_registration/registration/forms.py
synapse_registration/registration/models.py
synapse_registration/registration/signals.py
synapse_registration/registration/tests.py
synapse_registration/registration/urls.py
synapse_registration/registration/views.py
synapse_registration/registration/management/__init__.py
synapse_registration/registration/management/commands/__init__.py
synapse_registration/registration/management/commands/cleanup.py
synapse_registration/registration/migrations/0001_initial.py
synapse_registration/registration/migrations/0002_alter_userregistration_email_and_more.py
synapse_registration/registration/migrations/0003_userregistration_timestamp_and_more.py
synapse_registration/registration/migrations/0004_userregistration_mod_message_userregistration_notify.py
synapse_registration/registration/migrations/0005_emailblock_ipblock_usernamerule.py
synapse_registration/registration/migrations/0006_alter_userregistration_status.py
synapse_registration/registration/migrations/__init__.py
synapse_registration/registration/static/matrix-logo-white.svg
synapse_registration/registration/templates/404.html
synapse_registration/registration/templates/500.html
synapse_registration/registration/templates/base.html
synapse_registration/registration/templates/error_page.html
synapse_registration/registration/templates/landing_page.html
synapse_registration/registration/templates/admin/base_site.html
synapse_registration/registration/templates/registration/already_verified.html
synapse_registration/registration/templates/registration/complete_registration.html
synapse_registration/registration/templates/registration/email_form.html
synapse_registration/registration/templates/registration/email_sent.html
synapse_registration/registration/templates/registration/password_set_success.html
synapse_registration-0.1.3.dist-info/METADATA
synapse_registration-0.1.3.dist-info/WHEEL
synapse_registration-0.1.3.dist-info/entry_points.txt
synapse_registration-0.1.3.dist-info/licenses/LICENSE
synapse_registration-0.1.3.dist-info/RECORD
