Metadata-Version: 2.4
Name: synapse_registration
Version: 0.1.3
Summary: A Django app for allowing users to register for a Synapse account.
Project-URL: Homepage, https://git.private.coffee/privatecoffee/synapse-registration
Project-URL: Bug Tracker, https://git.private.coffee/privatecoffee/synapse-registration/issues
Project-URL: Source Code, https://git.private.coffee/privatecoffee/synapse-registration
Author-email: "Private.coffee Team" <support@private.coffee>
License: Copyright (c) 2024 Private.coffee Team <support@private.coffee>
License-File: LICENSE
Classifier: License :: OSI Approved :: MIT License
Classifier: Operating System :: OS Independent
Classifier: Programming Language :: Python :: 3
Requires-Python: >=3.11
Requires-Dist: django
Requires-Dist: django-mjml
Requires-Dist: pyyaml
Requires-Dist: requests
